criterion.cp37-win_amd64.pyd
ddop/__init__.py
ddop/datasets/__init__.py
ddop/datasets/load_datasets.py
ddop/datasets/data/yaz_multioutput.csv
ddop/datasets/data/yaz_steak.csv
ddop/metrics/__init__.py
ddop/metrics/costs.py
ddop/metrics/tests/__init__.py
ddop/metrics/tests/test_costs.py
ddop/newsvendor/DecisionTreeNewsvendor.py
ddop/newsvendor/DeepLearningNewsvendor.py
ddop/newsvendor/EmpiricalRiskMinimizationNewsvendor.py
ddop/newsvendor/KernelOptimizationNewsvendor.py
ddop/newsvendor/LightGradientBoostingNewsvendor.py
ddop/newsvendor/RandomForestNewsvendor.py
ddop/newsvendor/__init__.py
ddop/newsvendor/base.py
ddop/newsvendor/tests/__init__.py
ddop/newsvendor/tests/test_KernelOptimizationNV.py
ddop/utils/__init__.py
ddop/utils/criterion.c
ddop/utils/criterion.cp37-win_amd64.pyd
ddop/utils/kernels.py
ddop/utils/validation.py
ddop-0.3.4.dist-info/LICENSE
ddop-0.3.4.dist-info/METADATA
ddop-0.3.4.dist-info/WHEEL
ddop-0.3.4.dist-info/top_level.txt
ddop-0.3.4.dist-info/RECORD
