Metadata-Version: 2.1
Name: ddop
Version: 0.3.4
Summary: Package for data-driven operations management
Home-page: UNKNOWN
Author: Andreas Philippi
Author-email: 
License: MIT
Platform: UNKNOWN
Requires-Python: >=3.6
Requires-Dist: Cython
Requires-Dist: scikit-learn (>=0.23.0)
Requires-Dist: pandas
Requires-Dist: PuLP (==2.0)
Requires-Dist: tensorflow (==2.1.0)
Requires-Dist: Keras (==2.3.1)
Requires-Dist: numpy (==1.18.2)
Requires-Dist: scipy (==1.4.1)
